{
  "id": "mock-doc-id",
  "url": null,
  "type": "blog_post",
  "href": null,
  "tags": [],
  "first_publication_date": "1970-01-01T00:00:01+0000",
  "last_publication_date": "1970-01-01T00:00:01+0000",
  "slugs": [],
  "linked_documents": [],
  "lang": "en-us",
  "alternate_languages": [],
  "data": {
    "title": "sang",
    "category": {
      "id": "mock_document_id",
      "link_type": "Document",
      "type": "category",
      "tags": [],
      "lang": "en-us",
      "slug": null,
      "first_publication_date": "1970-01-01T00:00:01+0000",
      "last_publication_date": "1970-01-01T01:00:00+0000"
    },
    "author": [
      {
        "author": {
          "id": "mock_document_id",
          "link_type": "Document",
          "type": "author",
          "tags": [],
          "lang": "en-us",
          "slug": null,
          "first_publication_date": "1970-01-01T00:00:01+0000",
          "last_publication_date": "1970-01-01T01:00:00+0000"
        }
      }
    ],
    "date": "2013-10-08",
    "thumbnail": {
      "dimensions": {
        "width": 900,
        "height": 500
      },
      "alt": null,
      "copyright": null,
      "url": "https://images.unsplash.com/photo-1606248897732-2c5ffe759c04"
    },
    "summary": [
      {
        "type": "paragraph",
        "text": "Nulla ex voluptate culpa occaecat deserunt do ullamco amet. Labore consequat excepteur cillum in non sunt. Id Lorem sint laboris.",
        "spans": []
      }
    ],
    "slices": []
  }
}